pan_chainguard/__init__.py
pan_chainguard/ccadb.py
pan_chainguard/crtsh.py
pan_chainguard/mozilla.py
pan_chainguard/util.py
pan_chainguard-0.12.0.data/scripts/cert-fingerprints.sh
pan_chainguard-0.12.0.data/scripts/chain.py
pan_chainguard-0.12.0.data/scripts/chainring.py
pan_chainguard-0.12.0.data/scripts/fling.py
pan_chainguard-0.12.0.data/scripts/guard.py
pan_chainguard-0.12.0.data/scripts/link.py
pan_chainguard-0.12.0.data/scripts/sprocket.py
pan_chainguard-0.12.0.dist-info/licenses/LICENSE.txt
pan_chainguard-0.12.0.dist-info/METADATA
pan_chainguard-0.12.0.dist-info/WHEEL
pan_chainguard-0.12.0.dist-info/top_level.txt
pan_chainguard-0.12.0.dist-info/RECORD
