Metadata-Version: 2.4
Name: pan-chainguard
Version: 0.12.0
Summary: Manage Root Store and Intermediate Certificate Chains on PAN-OS
Home-page: https://github.com/PaloAltoNetworks/pan-chainguard
Author: Palo Alto Networks, Inc.
Author-email: devrel@paloaltonetworks.com
License: ISC
Classifier: Programming Language :: Python :: 3
Classifier: License :: OSI Approved :: ISC License (ISCL)
Requires-Python: >=3.9
License-File: LICENSE.txt
Requires-Dist: aiohttp>=3.9.0
Requires-Dist: pan-python>=0.25.0
Requires-Dist: treelib>=1.7.0
Dynamic: license-file
